{"status": "📊 **وضعیت تفصیلی سرور:**\n➖➖➖➖➖➖➖➖➖➖➖➖\n🤖 **وضعیت ربات:**\n▫️ وضعیت: `فعال ✅`\n\n💻 **اطلاعات سیستم:**\n▫️ سیستم عامل: `Linux-6.2.16-x86_64-with-glibc2.40`\n▫️ معماری: `x86_64`\n▫️ پایتون: `3.11.10`\n▫️ پردازنده: `نامشخص`\n\n🔄 **وضعیت CPU:**\n▫️ استفاده: `20.2%`\n▫️ تعداد هسته: `8`\n▫️ فرکانس: `3050.0 MHz`\n▫️ روند: `🟢 پایدار`\n▫️ پیش‌بینی: `وضعیت پایدار برای هفته آینده`\n\n💾 **وضعیت RAM:**\n▫️ کل: `62.81 GB`\n▫️ استفاده شده: `41.87 GB (67.7%)`\n▫️ آزاد: `20.26 GB`\n▫️ روند: `🟡 ثابت (نیاز به توجه)`\n▫️ پیش‌بینی: `احتمال افزایش مصرف در روزهای آینده`\n\n💿 **وضعیت SWAP:**\n▫️ کل: `0.00 B`\n▫️ استفاده شده: `0.00 B (0.0%)`\n▫️ آزاد: `0.00 B`\n\n💽 **وضعیت دیسک:**\n▫️ کل: `49.12 GB`\n▫️ استفاده شده: `20.97 GB (44.6%)`\n▫️ آزاد: `26.08 GB`\n▫️ روند: `🟢 پایدار`\n▫️ پیش‌بینی: `وضعیت پایدار برای هفته آینده`\n\n🌐 **وضعیت شبکه:**\n▫️ دریافت شده: `89.52 MB`\n▫️ ارسال شده: `17.26 MB`\n▫️ خطاهای دریافت: `0`\n▫️ خطاهای ارسال: `0`\n\n⏰ **اطلاعات زمانی:**\n▫️ زمان سرور: `2025-03-19 10:55:35`\n▫️ زمان راه‌اندازی: `2025-03-19 07:06:13`\n▫️ مدت کارکرد: `3:49:22`\n\n📝 **وضعیت فرایندها:**\n▫️ تعداد کل: `15`\n", "timestamp": "2025-03-19T10:55:35.434884", "details": {"cpu_usage": 20.2, "ram_usage": 67.7, "disk_usage": 44.6, "predictions": {"cpu": "وضعیت پایدار برای هفته آینده", "ram": "احتمال افزایش مصرف در روزهای آینده", "disk": "وضعیت پایدار برای هفته آینده"}}}